CHANGES.rst
DESCRIPTION.rst
LICENSE
MANIFEST.in
README.md
setup.py
src/ldc_tint/__init__.py
src/ldc_tint/class_lister.py
src/ldc_tint.egg-info/PKG-INFO
src/ldc_tint.egg-info/SOURCES.txt
src/ldc_tint.egg-info/dependency_links.txt
src/ldc_tint.egg-info/entry_points.txt
src/ldc_tint.egg-info/requires.txt
src/ldc_tint.egg-info/top_level.txt
src/ldc_tint/filter/__init__.py
src/ldc_tint/filter/_demacronize.py
src/ldc_tint/filter/_detect_maori.py