Metadata-Version: 2.1
Name: ldc-tint
Version: 0.0.3
Summary: Python3 library containing plugins for llm-dataset-converter specific to Tikanga in Technology project (TinT).
Home-page: https://github.com/waikato-llm/ldc-tint
Author: Peter Reutemann
Author-email: fracpete@waikato.ac.nz
License: MIT License
Classifier: Development Status :: 4 - Beta
Classifier: License :: OSI Approved :: MIT License
Classifier: Topic :: Scientific/Engineering :: Artificial Intelligence
Classifier: Programming Language :: Python :: 3
License-File: LICENSE
